{
	"info": {
		"_postman_id": "d8410414-49cd-48be-9378-117903a964d2",
		"name": "notes-backend",
		"schema": "https://schema.getpostman.com/json/collection/v2.1.0/collection.json",
		"_exporter_id": "6118536"
	},
	"item": [
		{
			"name": "auth",
			"item": [
				{
					"name": "login",
					"event": [
						{
							"listen": "test",
							"script": {
								"exec": [
									"pm.collectionVariables.set(\"accessToken\", pm.response.json().accessToken);\r",
									"pm.collectionVariables.set(\"userId\", pm.response.json().user.id);"
								],
								"type": "text/javascript",
								"packages": {}
							}
						}
					],
					"request": {
						"method": "POST",
						"header": [],
						"body": {
							"mode": "raw",
							"raw": "{\r\n    \"email\": \"superuser@correo.com\",\r\n    \"password\": \"superpassword\"\r\n}",
							"options": {
								"raw": {
									"language": "json"
								}
							}
						},
						"url": {
							"raw": "http://localhost:3000/api/auth/login",
							"protocol": "http",
							"host": [
								"localhost"
							],
							"port": "3000",
							"path": [
								"api",
								"auth",
								"login"
							]
						}
					},
					"response": []
				}
			]
		},
		{
			"name": "users",
			"item": [
				{
					"name": "Create user",
					"request": {
						"auth": {
							"type": "bearer",
							"bearer": [
								{
									"key": "token",
									"value": "{{accessToken}}",
									"type": "string"
								}
							]
						},
						"method": "POST",
						"header": [],
						"body": {
							"mode": "raw",
							"raw": "{\r\n    \"email\": \"test1@correo.com\",\r\n    \"password\": \"12345678\"\r\n}",
							"options": {
								"raw": {
									"language": "json"
								}
							}
						},
						"url": {
							"raw": "http://localhost:3000/api/users",
							"protocol": "http",
							"host": [
								"localhost"
							],
							"port": "3000",
							"path": [
								"api",
								"users"
							]
						}
					},
					"response": []
				},
				{
					"name": "Create admin",
					"request": {
						"auth": {
							"type": "bearer",
							"bearer": [
								{
									"key": "token",
									"value": "{{accessToken}}",
									"type": "string"
								}
							]
						},
						"method": "POST",
						"header": [],
						"body": {
							"mode": "raw",
							"raw": "{\r\n    \"email\": \"test0@correo.com\",\r\n    \"password\": \"12345678\",\r\n    \"role\": \"admin\"\r\n}",
							"options": {
								"raw": {
									"language": "json"
								}
							}
						},
						"url": {
							"raw": "http://localhost:3000/api/users",
							"protocol": "http",
							"host": [
								"localhost"
							],
							"port": "3000",
							"path": [
								"api",
								"users"
							]
						}
					},
					"response": []
				},
				{
					"name": "list of users",
					"request": {
						"auth": {
							"type": "bearer",
							"bearer": [
								{
									"key": "token",
									"value": "{{accessToken}}",
									"type": "string"
								}
							]
						},
						"method": "GET",
						"header": [],
						"url": {
							"raw": "http://localhost:3000/api/users?page=1&limit=10",
							"protocol": "http",
							"host": [
								"localhost"
							],
							"port": "3000",
							"path": [
								"api",
								"users"
							],
							"query": [
								{
									"key": "page",
									"value": "1"
								},
								{
									"key": "limit",
									"value": "10"
								}
							]
						}
					},
					"response": []
				},
				{
					"name": "user detail",
					"request": {
						"auth": {
							"type": "bearer",
							"bearer": [
								{
									"key": "token",
									"value": "{{accessToken}}",
									"type": "string"
								}
							]
						},
						"method": "GET",
						"header": [],
						"url": {
							"raw": "http://localhost:3000/api/users/:id",
							"protocol": "http",
							"host": [
								"localhost"
							],
							"port": "3000",
							"path": [
								"api",
								"users",
								":id"
							],
							"variable": [
								{
									"key": "id",
									"value": "6a506053-0117-4b76-8057-9b334a6341b7"
								}
							]
						}
					},
					"response": []
				},
				{
					"name": "change password",
					"request": {
						"auth": {
							"type": "bearer",
							"bearer": [
								{
									"key": "token",
									"value": "{{accessToken}}",
									"type": "string"
								}
							]
						},
						"method": "PATCH",
						"header": [],
						"body": {
							"mode": "raw",
							"raw": "{\r\n    \"password\": \"123456789\"\r\n}",
							"options": {
								"raw": {
									"language": "json"
								}
							}
						},
						"url": {
							"raw": "http://localhost:3000/api/users/:userId/password",
							"protocol": "http",
							"host": [
								"localhost"
							],
							"port": "3000",
							"path": [
								"api",
								"users",
								":userId",
								"password"
							],
							"variable": [
								{
									"key": "userId",
									"value": "5c961b8d-6bf5-4190-af73-6fee2c6eab3c"
								}
							]
						}
					},
					"response": []
				},
				{
					"name": "delete user",
					"request": {
						"auth": {
							"type": "bearer",
							"bearer": [
								{
									"key": "token",
									"value": "{{accessToken}}",
									"type": "string"
								}
							]
						},
						"method": "DELETE",
						"header": [],
						"url": {
							"raw": "http://localhost:3000/api/users/:userId",
							"protocol": "http",
							"host": [
								"localhost"
							],
							"port": "3000",
							"path": [
								"api",
								"users",
								":userId"
							],
							"variable": [
								{
									"key": "userId",
									"value": "0d1e5628-32e1-4f20-a9fc-0ae95c7c9ade"
								}
							]
						}
					},
					"response": []
				}
			]
		},
		{
			"name": "notes",
			"item": [
				{
					"name": "create notes",
					"request": {
						"auth": {
							"type": "bearer",
							"bearer": [
								{
									"key": "token",
									"value": "{{accessToken}}",
									"type": "string"
								}
							]
						},
						"method": "POST",
						"header": [],
						"body": {
							"mode": "raw",
							"raw": "{\r\n    \"title\":\"hola mundo\",\r\n    \"description\": \"alguna cosa\"\r\n}",
							"options": {
								"raw": {
									"language": "json"
								}
							}
						},
						"url": {
							"raw": "http://localhost:3000/api/notes",
							"protocol": "http",
							"host": [
								"localhost"
							],
							"port": "3000",
							"path": [
								"api",
								"notes"
							]
						}
					},
					"response": []
				},
				{
					"name": "list note with filters",
					"request": {
						"auth": {
							"type": "bearer",
							"bearer": [
								{
									"key": "token",
									"value": "{{accessToken}}",
									"type": "string"
								}
							]
						},
						"method": "GET",
						"header": [],
						"url": {
							"raw": "http://localhost:3000/api/notes?status=active",
							"protocol": "http",
							"host": [
								"localhost"
							],
							"port": "3000",
							"path": [
								"api",
								"notes"
							],
							"query": [
								{
									"key": "search",
									"value": "algunas",
									"disabled": true
								},
								{
									"key": "status",
									"value": "active"
								},
								{
									"key": "page",
									"value": "1",
									"disabled": true
								},
								{
									"key": "limit",
									"value": "10",
									"disabled": true
								}
							]
						}
					},
					"response": []
				},
				{
					"name": "detail",
					"request": {
						"auth": {
							"type": "bearer",
							"bearer": [
								{
									"key": "token",
									"value": "{{accessToken}}",
									"type": "string"
								}
							]
						},
						"method": "GET",
						"header": [],
						"url": {
							"raw": "http://localhost:3000/api/notes/:noteId",
							"protocol": "http",
							"host": [
								"localhost"
							],
							"port": "3000",
							"path": [
								"api",
								"notes",
								":noteId"
							],
							"variable": [
								{
									"key": "noteId",
									"value": "2a8d190f-c4d2-4fcb-bb50-19acb28533ce"
								}
							]
						}
					},
					"response": []
				},
				{
					"name": "stats",
					"request": {
						"auth": {
							"type": "bearer",
							"bearer": [
								{
									"key": "token",
									"value": "{{accessToken}}",
									"type": "string"
								}
							]
						},
						"method": "GET",
						"header": [],
						"url": {
							"raw": "http://localhost:3000/api/notes/stats",
							"protocol": "http",
							"host": [
								"localhost"
							],
							"port": "3000",
							"path": [
								"api",
								"notes",
								"stats"
							]
						}
					},
					"response": []
				},
				{
					"name": "recent",
					"request": {
						"auth": {
							"type": "bearer",
							"bearer": [
								{
									"key": "token",
									"value": "{{accessToken}}",
									"type": "string"
								}
							]
						},
						"method": "GET",
						"header": [],
						"url": {
							"raw": "http://localhost:3000/api/notes/recent?limit=5",
							"protocol": "http",
							"host": [
								"localhost"
							],
							"port": "3000",
							"path": [
								"api",
								"notes",
								"recent"
							],
							"query": [
								{
									"key": "limit",
									"value": "5"
								}
							]
						}
					},
					"response": []
				},
				{
					"name": "update note",
					"request": {
						"auth": {
							"type": "bearer",
							"bearer": [
								{
									"key": "token",
									"value": "{{accessToken}}",
									"type": "string"
								}
							]
						},
						"method": "PATCH",
						"header": [],
						"body": {
							"mode": "raw",
							"raw": "{\r\n    \"title\": \"hola mundo edit\",\r\n    \"description\": \"receta de cocina\",\r\n    \"status\": \"active\"\r\n}",
							"options": {
								"raw": {
									"language": "json"
								}
							}
						},
						"url": {
							"raw": "http://localhost:3000/api/notes/:noteId",
							"protocol": "http",
							"host": [
								"localhost"
							],
							"port": "3000",
							"path": [
								"api",
								"notes",
								":noteId"
							],
							"variable": [
								{
									"key": "noteId",
									"value": "2a8d190f-c4d2-4fcb-bb50-19acb28533ce"
								}
							]
						}
					},
					"response": []
				},
				{
					"name": "delete note",
					"request": {
						"auth": {
							"type": "bearer",
							"bearer": [
								{
									"key": "token",
									"value": "{{accessToken}}",
									"type": "string"
								}
							]
						},
						"method": "DELETE",
						"header": [],
						"url": {
							"raw": "http://localhost:3000/api/notes/:id",
							"protocol": "http",
							"host": [
								"localhost"
							],
							"port": "3000",
							"path": [
								"api",
								"notes",
								":id"
							],
							"variable": [
								{
									"key": "id",
									"value": "5dc26adf-4ffd-45f8-b4ec-5358d3156a0b"
								}
							]
						}
					},
					"response": []
				},
				{
					"name": "share",
					"request": {
						"auth": {
							"type": "bearer",
							"bearer": [
								{
									"key": "token",
									"value": "{{accessToken}}",
									"type": "string"
								}
							]
						},
						"method": "POST",
						"header": [],
						"body": {
							"mode": "raw",
							"raw": "{\r\n    \"description\": \"comparto con la gente del club\",\r\n    \"expiresAt\": \"2025-12-11\"\r\n}",
							"options": {
								"raw": {
									"language": "json"
								}
							}
						},
						"url": {
							"raw": "http://localhost:3000/api/notes/:noteId/share",
							"protocol": "http",
							"host": [
								"localhost"
							],
							"port": "3000",
							"path": [
								"api",
								"notes",
								":noteId",
								"share"
							],
							"variable": [
								{
									"key": "noteId",
									"value": "820bdd96-4d7a-4edf-8f85-62846a572ea7"
								}
							]
						}
					},
					"response": []
				},
				{
					"name": "shared list",
					"request": {
						"auth": {
							"type": "bearer",
							"bearer": [
								{
									"key": "token",
									"value": "{{accessToken}}",
									"type": "string"
								}
							]
						},
						"method": "GET",
						"header": [],
						"url": {
							"raw": "http://localhost:3000/api/notes/shared?page=1&limit=10",
							"protocol": "http",
							"host": [
								"localhost"
							],
							"port": "3000",
							"path": [
								"api",
								"notes",
								"shared"
							],
							"query": [
								{
									"key": "page",
									"value": "1"
								},
								{
									"key": "limit",
									"value": "10"
								}
							]
						}
					},
					"response": []
				},
				{
					"name": "update share",
					"request": {
						"auth": {
							"type": "bearer",
							"bearer": [
								{
									"key": "token",
									"value": "{{accessToken}}",
									"type": "string"
								}
							]
						},
						"method": "PATCH",
						"header": [],
						"body": {
							"mode": "raw",
							"raw": "{\r\n    \"description\": \"comparto con la gente del club editado\",\r\n    \"expiresAt\": \"2025-09-22T00:00:00.000Z\"\r\n}",
							"options": {
								"raw": {
									"language": "json"
								}
							}
						},
						"url": {
							"raw": "http://localhost:3000/api/notes/shared/:publicId",
							"protocol": "http",
							"host": [
								"localhost"
							],
							"port": "3000",
							"path": [
								"api",
								"notes",
								"shared",
								":publicId"
							],
							"variable": [
								{
									"key": "publicId",
									"value": "5a249857-78d0-4fd6-976d-b4c196e97a72"
								}
							]
						}
					},
					"response": []
				},
				{
					"name": "remove share",
					"request": {
						"auth": {
							"type": "bearer",
							"bearer": [
								{
									"key": "token",
									"value": "{{accessToken}}",
									"type": "string"
								}
							]
						},
						"method": "DELETE",
						"header": [],
						"url": {
							"raw": "http://localhost:3000/api/notes/shared/:publicId",
							"protocol": "http",
							"host": [
								"localhost"
							],
							"port": "3000",
							"path": [
								"api",
								"notes",
								"shared",
								":publicId"
							],
							"variable": [
								{
									"key": "publicId",
									"value": "eb7bd65f-1b09-4c08-81ad-68f4c4c00675"
								}
							]
						}
					},
					"response": []
				},
				{
					"name": "shared stats",
					"request": {
						"auth": {
							"type": "bearer",
							"bearer": [
								{
									"key": "token",
									"value": "{{accessToken}}",
									"type": "string"
								}
							]
						},
						"method": "GET",
						"header": [],
						"url": {
							"raw": "http://localhost:3000/api/notes/shared/stats",
							"protocol": "http",
							"host": [
								"localhost"
							],
							"port": "3000",
							"path": [
								"api",
								"notes",
								"shared",
								"stats"
							]
						}
					},
					"response": []
				}
			]
		},
		{
			"name": "public",
			"item": [
				{
					"name": "get public note",
					"request": {
						"auth": {
							"type": "noauth"
						},
						"method": "GET",
						"header": [],
						"url": {
							"raw": "http://localhost:3000/api/public/notes/:publicId",
							"protocol": "http",
							"host": [
								"localhost"
							],
							"port": "3000",
							"path": [
								"api",
								"public",
								"notes",
								":publicId"
							],
							"variable": [
								{
									"key": "publicId",
									"value": "12207db5-59a5-4f3e-8bfe-7da439bae4fe"
								}
							]
						}
					},
					"response": []
				}
			]
		},
		{
			"name": "health",
			"item": [
				{
					"name": "get public health",
					"request": {
						"method": "GET",
						"header": [],
						"url": {
							"raw": "http://localhost:3000/api/public/health",
							"protocol": "http",
							"host": [
								"localhost"
							],
							"port": "3000",
							"path": [
								"api",
								"public",
								"health"
							]
						}
					},
					"response": []
				},
				{
					"name": "get general health",
					"request": {
						"method": "GET",
						"header": [],
						"url": {
							"raw": "http://localhost:3000/api/health",
							"protocol": "http",
							"host": [
								"localhost"
							],
							"port": "3000",
							"path": [
								"api",
								"health"
							]
						}
					},
					"response": []
				},
				{
					"name": "get dabatase health",
					"request": {
						"method": "GET",
						"header": [],
						"url": {
							"raw": "http://localhost:3000/api/health/database",
							"protocol": "http",
							"host": [
								"localhost"
							],
							"port": "3000",
							"path": [
								"api",
								"health",
								"database"
							]
						}
					},
					"response": []
				}
			]
		}
	],
	"variable": [
		{
			"key": "accessToken",
			"value": ""
		},
		{
			"key": "userId",
			"value": ""
		}
	]
}